cubic/__init__.py
cubic/client/__init__.py
cubic/client/file_client.py
cubic/client/s3_client.py
cubic/client/sqream_client.py
cubic/rest/__init__.py
dev.cubic-0.1.3.1.dist-info/METADATA
dev.cubic-0.1.3.1.dist-info/WHEEL
dev.cubic-0.1.3.1.dist-info/top_level.txt
dev.cubic-0.1.3.1.dist-info/RECORD
