Metadata-Version: 2.1
Name: dev.cubic
Version: 0.1.3.1
Summary: UNKNOWN
Home-page: UNKNOWN
License: UNKNOWN
Platform: UNKNOWN
Requires-Dist: python-decouple
Requires-Dist: requests
